{
  "target_column": "Total Revenue",
  "features": [
    {
      "name": "Region",
      "type": "categorical",
      "options": [
        "Asia",
        "Australia and Oceania",
        "Central America and the Caribbean",
        "Europe",
        "Middle East and North Africa",
        "North America",
        "Sub-Saharan Africa"
      ]
    },
    {
      "name": "Country",
      "type": "categorical",
      "options": [
        "Afghanistan",
        "Albania",
        "Algeria",
        "Andorra",
        "Angola",
        "Antigua and Barbuda ",
        "Armenia",
        "Australia",
        "Austria",
        "Azerbaijan",
        "Bahrain",
        "Bangladesh",
        "Barbados",
        "Belarus",
        "Belgium",
        "Belize",
        "Benin",
        "Bhutan",
        "Bosnia and Herzegovina",
        "Botswana",
        "Brunei",
        "Bulgaria",
        "Burkina Faso",
        "Burundi",
        "Cambodia",
        "Cameroon",
        "Canada",
        "Cape Verde",
        "Central African Republic",
        "Chad",
        "China",
        "Comoros",
        "Costa Rica",
        "Cote d'Ivoire",
        "Croatia",
        "Cuba",
        "Cyprus",
        "Czech Republic",
        "Democratic Republic of the Congo",
        "Denmark",
        "Djibouti",
        "Dominica",
        "Dominican Republic",
        "East Timor",
        "Egypt",
        "El Salvador",
        "Equatorial Guinea",
        "Eritrea",
        "Estonia",
        "Ethiopia",
        "Federated States of Micronesia",
        "Fiji",
        "Finland",
        "France",
        "Gabon",
        "Georgia",
        "Germany",
        "Ghana",
        "Greece",
        "Greenland",
        "Grenada",
        "Guatemala",
        "Guinea",
        "Guinea-Bissau",
        "Haiti",
        "Honduras",
        "Hungary",
        "Iceland",
        "India",
        "Indonesia",
        "Iran",
        "Iraq",
        "Ireland",
        "Israel",
        "Italy",
        "Jamaica",
        "Japan",
        "Jordan",
        "Kazakhstan",
        "Kenya",
        "Kiribati",
        "Kosovo",
        "Kuwait",
        "Kyrgyzstan",
        "Laos",
        "Latvia",
        "Lebanon",
        "Lesotho",
        "Liberia",
        "Libya",
        "Liechtenstein",
        "Lithuania",
        "Luxembourg",
        "Macedonia",
        "Madagascar",
        "Malawi",
        "Malaysia",
        "Maldives",
        "Mali",
        "Malta"
      ]
    },
    {
      "name": "Item Type",
      "type": "categorical",
      "options": [
        "Baby Food",
        "Beverages",
        "Cereal",
        "Clothes",
        "Cosmetics",
        "Fruits",
        "Household",
        "Meat",
        "Office Supplies",
        "Personal Care",
        "Snacks",
        "Vegetables"
      ]
    },
    {
      "name": "Sales Channel",
      "type": "categorical",
      "options": [
        "Offline",
        "Online"
      ]
    },
    {
      "name": "Order Priority",
      "type": "categorical",
      "options": [
        "C",
        "H",
        "L",
        "M"
      ]
    },
    {
      "name": "Order ID",
      "type": "numeric"
    },
    {
      "name": "Ship Date",
      "type": "categorical",
      "options": [
        "1/1/2011",
        "1/1/2012",
        "1/1/2013",
        "1/1/2014",
        "1/1/2015",
        "1/1/2016",
        "1/1/2017",
        "1/10/2011",
        "1/10/2012",
        "1/10/2013",
        "1/10/2014",
        "1/10/2015",
        "1/10/2016",
        "1/10/2017",
        "1/11/2010",
        "1/11/2011",
        "1/11/2012",
        "1/11/2013",
        "1/11/2015",
        "1/11/2016",
        "1/11/2017",
        "1/12/2010",
        "1/12/2011",
        "1/12/2012",
        "1/12/2013",
        "1/12/2014",
        "1/12/2015",
        "1/12/2016",
        "1/12/2017",
        "1/13/2010",
        "1/13/2011",
        "1/13/2012",
        "1/13/2013",
        "1/13/2014",
        "1/13/2015",
        "1/13/2016",
        "1/13/2017",
        "1/14/2011",
        "1/14/2013",
        "1/14/2015",
        "1/14/2016",
        "1/14/2017",
        "1/15/2011",
        "1/15/2012",
        "1/15/2013",
        "1/15/2014",
        "1/15/2015",
        "1/15/2016",
        "1/15/2017",
        "1/16/2010",
        "1/16/2011",
        "1/16/2012",
        "1/16/2013",
        "1/16/2014",
        "1/16/2015",
        "1/16/2016",
        "1/16/2017",
        "1/17/2010",
        "1/17/2011",
        "1/17/2012",
        "1/17/2013",
        "1/17/2015",
        "1/17/2016",
        "1/17/2017",
        "1/18/2010",
        "1/18/2011",
        "1/18/2012",
        "1/18/2013",
        "1/18/2014",
        "1/18/2015",
        "1/18/2016",
        "1/18/2017",
        "1/19/2011",
        "1/19/2012",
        "1/19/2013",
        "1/19/2014",
        "1/19/2015",
        "1/19/2016",
        "1/19/2017",
        "1/2/2012",
        "1/2/2013",
        "1/2/2014",
        "1/2/2015",
        "1/2/2016",
        "1/2/2017",
        "1/20/2010",
        "1/20/2011",
        "1/20/2012",
        "1/20/2013",
        "1/20/2014",
        "1/20/2015",
        "1/20/2016",
        "1/20/2017",
        "1/21/2010",
        "1/21/2011",
        "1/21/2012",
        "1/21/2013",
        "1/21/2014",
        "1/21/2015",
        "1/21/2016"
      ]
    },
    {
      "name": "Units Sold",
      "type": "numeric"
    },
    {
      "name": "Unit Price",
      "type": "numeric"
    },
    {
      "name": "Unit Cost",
      "type": "numeric"
    },
    {
      "name": "Total Cost",
      "type": "numeric"
    },
    {
      "name": "Total Profit",
      "type": "numeric"
    },
    {
      "name": "day_of_week",
      "type": "numeric"
    },
    {
      "name": "month",
      "type": "numeric"
    },
    {
      "name": "day_of_year",
      "type": "numeric"
    }
  ]
}